prefeitura_rio/__init__.py
prefeitura_rio/core.py
prefeitura_rio/integrations/__init__.py
prefeitura_rio/integrations/sgrc/__init__.py
prefeitura_rio/integrations/sgrc/exceptions.py
prefeitura_rio/integrations/sgrc/models.py
prefeitura_rio/integrations/sgrc/utils.py
prefeitura_rio/metrics/__init__.py
prefeitura_rio/metrics/agnostic.py
prefeitura_rio/pipelines_utils/__init__.py
prefeitura_rio/pipelines_utils/bd.py
prefeitura_rio/pipelines_utils/dbt.py
prefeitura_rio/pipelines_utils/env.py
prefeitura_rio/pipelines_utils/gcs.py
prefeitura_rio/pipelines_utils/infisical.py
prefeitura_rio/pipelines_utils/io.py
prefeitura_rio/pipelines_utils/logging.py
prefeitura_rio/pipelines_utils/prefect.py
prefeitura_rio/pipelines_utils/state_handlers.py
prefeitura_rio/utils.py
prefeitura_rio-1.1.3.dist-info/LICENSE
prefeitura_rio-1.1.3.dist-info/METADATA
prefeitura_rio-1.1.3.dist-info/WHEEL
prefeitura_rio-1.1.3.dist-info/RECORD
